README.rst
setup.py
sql_importer/__init__.py
sql_importer/cursors.py
sql_importer.egg-info/PKG-INFO
sql_importer.egg-info/SOURCES.txt
sql_importer.egg-info/dependency_links.txt
sql_importer.egg-info/top_level.txt
sql_importer/loaders/__init__.py
sql_importer/loaders/postgresql.py
tests/postgresql/__init__.py
tests/postgresql/conftest.py
tests/postgresql/test_import.py
tests/postgresql/sql/__init__.py