Metadata-Version: 1.1
Name: sql-importer
Version: 1.0.0
Summary: it enables sql files to be imported as a python module.
Home-page: UNKNOWN
Author: Beproud
Author-email: righ.m9@gmail.com,crohaco@beproud.jp
License: UNKNOWN
Keywords: sql
Platform: UNKNOWN
Classifier: Intended Audience :: Developers
Classifier: License :: OSI Approved :: MIT License
Classifier: Programming Language :: Python
Classifier: Topic :: Software Development
Classifier: Programming Language :: SQL
